{
  "navbar": {
    "home": "Home",
    "shop": "Shop",
    "collection": "Collection",
    "Blog": "Blog",
    "contact": "Contact",
    "logout": "Log out",
    "login": "Log in"
  },

  "options": {
    "options": "Options",
    "toggleTheme": "Theme",
    "toggleLang": "Lang.",
    "dark": "Dark",
    "light": "Light",
    "eng": "ENG",
    "geo": "GEO"
  },

  "product": {
    "addToCart": "Add to cart ",
    "termsHeader": "Terms and Conditions",
    "terms": "Lorem ipsum dolor sit amet consectetur adipisicing elit. Placeat in incidunt modi quas nostrum. Repellat assumenda expedita officiis, omnis sunt ratione possimus, exercitationem, optio veniam tempora eos maiores repudiandae magnam."
  },

  "blog": {
    "writeNew": "Write a Blogpost",
    "thumbIsReq": "Thumbnail image is required",
    "title": "Title",
    "text": "Text",
    "undo": "Undo",
    "edit": "Edit",
    "upload": "Upload",
    "imgError": "IMG must be less than 3.5 MB",
    "postedOn": "Posted on",
    "editFull": "Edit a Blogpost"
  },

  "goBackLinks": {
    "backTo": "Back To",
    "blog": "Blog"
  },

  "cart": {
    "yourCart": "Your Cart",
    "reviewAndManage": "Review and manage the items in your cart.",
    "clear": "Clear Cart",
    "total": "Total"
  },
  "contact": {
    "nameHolder": "NAME",
    "mailHolder": "EMAIL",
    "msgHolder": "MESSAGE",
    "addres": "221B Baker Street",
    "dontBeShy": "Don't Be Shy Hit Us Up!"
  },

  "profile": {
    "firstName": "First Name",
    "lastName": "Last Name",
    "username": "Username",
    "email": "Email",
    "save": "Save Changes",
    "edit": "Edit",
    "revert": "Revert",

    "dateOfBirth": "Date of Birth",
    "typeNewPass": "Type new password",
    "newPassHolder": "New password...",
    "confirmPass": "Confirm password",
    "confirmPassHolder": "Confirm password..."
  }
}
